[
    {
        "name": "Channel 1",
        "online": true,
        "players": 34
    },
    {
        "name": "Channel 2",
        "online": true,
        "players": 9
    },
    {
        "name": "Channel 3",
        "online": true,
        "players": 3
    },
    {
        "name": "Channel 4",
        "online": true,
        "players": 2
    },
    {
        "name": "Channel 5",
        "online": true,
        "players": 4
    },
    {
        "name": "Channel 6",
        "online": true,
        "players": 4
    },
    {
        "name": "Channel 7",
        "online": true,
        "players": 2
    },
    {
        "name": "Channel 8",
        "online": true,
        "players": 5
    },
    {
        "name": "Collab",
        "online": true,
        "players": 2
    },
    {
        "name": "Custom Enemy",
        "online": true,
        "players": 3
    },
    {
        "name": "Boss Rush",
        "online": true,
        "players": 2
    }
]